{
  "mode": "lookup_delivery_package_nr",
  "ts_utc": "2026-03-08T22:54:41.136175+00:00",
  "tokens_file": "C:\\ACC\\tmp\\gls_unlinked_2025_12_tokens_part1.txt",
  "tokens_loaded": 500,
  "batch_size": 50,
  "batches_run": 10,
  "timeouts": 0,
  "max_timeouts": 2,
  "matched_count": 445,
  "matches": [
    {
      "tracking_number": "30645546334",
      "order_id": 23093943
    },
    {
      "tracking_number": "30645587980",
      "order_id": 23361736
    },
    {
      "tracking_number": "30645588413",
      "order_id": 23396031
    },
    {
      "tracking_number": "30645620276",
      "order_id": 23509421
    },
    {
      "tracking_number": "30645620478",
      "order_id": 23520868
    },
    {
      "tracking_number": "30645635812",
      "order_id": 23569826
    },
    {
      "tracking_number": "30645636087",
      "order_id": 23589049
    },
    {
      "tracking_number": "30645636198",
      "order_id": 23595586
    },
    {
      "tracking_number": "30645645864",
      "order_id": 23621728
    },
    {
      "tracking_number": "30645645877",
      "order_id": 23622884
    },
    {
      "tracking_number": "30645645967",
      "order_id": 23629673
    },
    {
      "tracking_number": "30645646102",
      "order_id": 23640176
    },
    {
      "tracking_number": "30645646261",
      "order_id": 23649699
    },
    {
      "tracking_number": "30645648686",
      "order_id": 23663956
    },
    {
      "tracking_number": "30645651836",
      "order_id": 23731203
    },
    {
      "tracking_number": "30645686204",
      "order_id": 23997695
    },
    {
      "tracking_number": "30645715440",
      "order_id": 24120990
    },
    {
      "tracking_number": "30645715808",
      "order_id": 24141145
    },
    {
      "tracking_number": "30645715816",
      "order_id": 24141271
    },
    {
      "tracking_number": "30645725824",
      "order_id": 24175782
    },
    {
      "tracking_number": "30645725951",
      "order_id": 24181474
    },
    {
      "tracking_number": "30645726111",
      "order_id": 24188085
    },
    {
      "tracking_number": "30645726153",
      "order_id": 24190934
    },
    {
      "tracking_number": "30645727518",
      "order_id": 24198213
    },
    {
      "tracking_number": "30645727673",
      "order_id": 24208965
    },
    {
      "tracking_number": "30645727674",
      "order_id": 24208964
    },
    {
      "tracking_number": "30645727714",
      "order_id": 24211300
    },
    {
      "tracking_number": "30645727865",
      "order_id": 24223817
    },
    {
      "tracking_number": "30645728103",
      "order_id": 24238327
    },
    {
      "tracking_number": "30645728143",
      "order_id": 24241034
    },
    {
      "tracking_number": "30645728208",
      "order_id": 24243949
    },
    {
      "tracking_number": "30645728256",
      "order_id": 24246524
    },
    {
      "tracking_number": "30645728390",
      "order_id": 24253739
    },
    {
      "tracking_number": "30645730676",
      "order_id": 24264676
    },
    {
      "tracking_number": "30645730704",
      "order_id": 24265926
    },
    {
      "tracking_number": "30645730734",
      "order_id": 24267584
    },
    {
      "tracking_number": "30645730833",
      "order_id": 24274173
    },
    {
      "tracking_number": "30645731192",
      "order_id": 24299820
    },
    {
      "tracking_number": "30645731279",
      "order_id": 24304117
    },
    {
      "tracking_number": "30645731335",
      "order_id": 24310130
    },
    {
      "tracking_number": "30645745803",
      "order_id": 24346419
    },
    {
      "tracking_number": "30645745920",
      "order_id": 24353448
    },
    {
      "tracking_number": "30645745960",
      "order_id": 24356499
    },
    {
      "tracking_number": "30645746086",
      "order_id": 24364349
    },
    {
      "tracking_number": "30645746294",
      "order_id": 24378885
    },
    {
      "tracking_number": "30645746343",
      "order_id": 24381324
    },
    {
      "tracking_number": "30645746433",
      "order_id": 24387929
    },
    {
      "tracking_number": "30645759891",
      "order_id": 24410730
    },
    {
      "tracking_number": "30645760087",
      "order_id": 24425855
    },
    {
      "tracking_number": "30645771548",
      "order_id": 24433573
    },
    {
      "tracking_number": "30645771594",
      "order_id": 24436001
    },
    {
      "tracking_number": "30645771609",
      "order_id": 24436835
    },
    {
      "tracking_number": "30645771627",
      "order_id": 24437925
    },
    {
      "tracking_number": "30645771655",
      "order_id": 24439273
    },
    {
      "tracking_number": "30645771671",
      "order_id": 24440320
    },
    {
      "tracking_number": "30645771863",
      "order_id": 24454342
    },
    {
      "tracking_number": "30645772017",
      "order_id": 24468943
    },
    {
      "tracking_number": "30645772021",
      "order_id": 24468533
    },
    {
      "tracking_number": "30645772042",
      "order_id": 24470575
    },
    {
      "tracking_number": "30645772413",
      "order_id": 24502065
    },
    {
      "tracking_number": "30645790258",
      "order_id": 24513158
    },
    {
      "tracking_number": "30645790302",
      "order_id": 24516554
    },
    {
      "tracking_number": "30645790322",
      "order_id": 24517854
    },
    {
      "tracking_number": "30645790469",
      "order_id": 24546341
    },
    {
      "tracking_number": "30645790574",
      "order_id": 24552570
    },
    {
      "tracking_number": "30645790609",
      "order_id": 24556084
    },
    {
      "tracking_number": "30645790670",
      "order_id": 24560207
    },
    {
      "tracking_number": "30645790697",
      "order_id": 24563108
    },
    {
      "tracking_number": "30645790799",
      "order_id": 24571538
    },
    {
      "tracking_number": "30645790886",
      "order_id": 24577981
    },
    {
      "tracking_number": "30645791011",
      "order_id": 24589783
    },
    {
      "tracking_number": "30645791139",
      "order_id": 24599798
    },
    {
      "tracking_number": "30645791199",
      "order_id": 24602729
    },
    {
      "tracking_number": "30645791219",
      "order_id": 24603654
    },
    {
      "tracking_number": "30645791220",
      "order_id": 24603963
    },
    {
      "tracking_number": "30645791222",
      "order_id": 24604341
    },
    {
      "tracking_number": "30645803417",
      "order_id": 24606733
    },
    {
      "tracking_number": "30645803440",
      "order_id": 24608044
    },
    {
      "tracking_number": "30645803480",
      "order_id": 24610986
    },
    {
      "tracking_number": "30645803521",
      "order_id": 24613206
    },
    {
      "tracking_number": "30645803610",
      "order_id": 24619206
    },
    {
      "tracking_number": "30645803613",
      "order_id": 24619071
    },
    {
      "tracking_number": "30645803642",
      "order_id": 24620282
    },
    {
      "tracking_number": "30645803666",
      "order_id": 24621625
    },
    {
      "tracking_number": "30645803703",
      "order_id": 24623263
    },
    {
      "tracking_number": "30645803721",
      "order_id": 24625245
    },
    {
      "tracking_number": "30645803723",
      "order_id": 24625361
    },
    {
      "tracking_number": "30645803753",
      "order_id": 24626507
    },
    {
      "tracking_number": "30645803754",
      "order_id": 24626573
    },
    {
      "tracking_number": "30645803770",
      "order_id": 24627579
    },
    {
      "tracking_number": "30645803803",
      "order_id": 24629468
    },
    {
      "tracking_number": "30645803822",
      "order_id": 24630455
    },
    {
      "tracking_number": "30645803889",
      "order_id": 24634431
    },
    {
      "tracking_number": "30645803904",
      "order_id": 24635694
    },
    {
      "tracking_number": "30645803956",
      "order_id": 24638109
    },
    {
      "tracking_number": "30645804163",
      "order_id": 24650410
    },
    {
      "tracking_number": "30645804224",
      "order_id": 24653975
    },
    {
      "tracking_number": "30645804270",
      "order_id": 24655812
    },
    {
      "tracking_number": "30645804287",
      "order_id": 24656456
    },
    {
      "tracking_number": "30645804371",
      "order_id": 24663467
    },
    {
      "tracking_number": "30645818272",
      "order_id": 24665141
    },
    {
      "tracking_number": "30645818282",
      "order_id": 24665801
    },
    {
      "tracking_number": "30645818284",
      "order_id": 24665799
    },
    {
      "tracking_number": "30645818330",
      "order_id": 24669628
    },
    {
      "tracking_number": "30645818339",
      "order_id": 24671307
    },
    {
      "tracking_number": "30645818507",
      "order_id": 24682190
    },
    {
      "tracking_number": "30645818666",
      "order_id": 24689486
    },
    {
      "tracking_number": "30645818716",
      "order_id": 24692443
    },
    {
      "tracking_number": "30645818718",
      "order_id": 24692511
    },
    {
      "tracking_number": "30645818737",
      "order_id": 24693470
    },
    {
      "tracking_number": "30645826377",
      "order_id": 24698379
    },
    {
      "tracking_number": "30645826447",
      "order_id": 24701365
    },
    {
      "tracking_number": "30645826448",
      "order_id": 24701367
    },
    {
      "tracking_number": "30645826531",
      "order_id": 24705654
    },
    {
      "tracking_number": "30645826573",
      "order_id": 24706855
    },
    {
      "tracking_number": "30645826582",
      "order_id": 24707415
    },
    {
      "tracking_number": "30645826586",
      "order_id": 24707587
    },
    {
      "tracking_number": "30645826620",
      "order_id": 24709283
    },
    {
      "tracking_number": "30645826707",
      "order_id": 24714099
    },
    {
      "tracking_number": "30645826752",
      "order_id": 24716692
    },
    {
      "tracking_number": "30645826907",
      "order_id": 24726105
    },
    {
      "tracking_number": "30645826919",
      "order_id": 24726662
    },
    {
      "tracking_number": "30645826946",
      "order_id": 24727955
    },
    {
      "tracking_number": "30645827036",
      "order_id": 24734730
    },
    {
      "tracking_number": "30645827041",
      "order_id": 24734827
    },
    {
      "tracking_number": "30645827058",
      "order_id": 24735347
    },
    {
      "tracking_number": "30645827112",
      "order_id": 24738211
    },
    {
      "tracking_number": "30645827115",
      "order_id": 24738212
    },
    {
      "tracking_number": "30645827132",
      "order_id": 24739044
    },
    {
      "tracking_number": "30645827155",
      "order_id": 24740178
    },
    {
      "tracking_number": "30645827176",
      "order_id": 24740921
    },
    {
      "tracking_number": "30645827201",
      "order_id": 24742042
    },
    {
      "tracking_number": "30645831345",
      "order_id": 24748374
    },
    {
      "tracking_number": "30645831371",
      "order_id": 24749533
    },
    {
      "tracking_number": "30645831382",
      "order_id": 24750124
    },
    {
      "tracking_number": "30645831402",
      "order_id": 24751422
    },
    {
      "tracking_number": "30645831420",
      "order_id": 24752104
    },
    {
      "tracking_number": "30645831573",
      "order_id": 24759024
    },
    {
      "tracking_number": "30645831625",
      "order_id": 24761771
    },
    {
      "tracking_number": "30645831628",
      "order_id": 24761717
    },
    {
      "tracking_number": "30645831663",
      "order_id": 24763850
    },
    {
      "tracking_number": "30645831691",
      "order_id": 24765457
    },
    {
      "tracking_number": "30645831693",
      "order_id": 24765590
    },
    {
      "tracking_number": "30645831706",
      "order_id": 24766176
    },
    {
      "tracking_number": "30645831721",
      "order_id": 24767354
    },
    {
      "tracking_number": "30645831729",
      "order_id": 24767545
    },
    {
      "tracking_number": "30645831733",
      "order_id": 24767548
    },
    {
      "tracking_number": "30645831762",
      "order_id": 24769463
    },
    {
      "tracking_number": "30645831772",
      "order_id": 24769401
    },
    {
      "tracking_number": "30645831807",
      "order_id": 24771197
    },
    {
      "tracking_number": "30645831811",
      "order_id": 24771300
    },
    {
      "tracking_number": "30645831814",
      "order_id": 24771350
    },
    {
      "tracking_number": "30645831850",
      "order_id": 24773151
    },
    {
      "tracking_number": "30645831877",
      "order_id": 24775779
    },
    {
      "tracking_number": "30645831881",
      "order_id": 24775778
    },
    {
      "tracking_number": "30645831882",
      "order_id": 24775827
    },
    {
      "tracking_number": "30645831929",
      "order_id": 24778852
    },
    {
      "tracking_number": "30645831930",
      "order_id": 24778854
    },
    {
      "tracking_number": "30645832002",
      "order_id": 24782300
    },
    {
      "tracking_number": "30645832016",
      "order_id": 24783768
    },
    {
      "tracking_number": "30645832017",
      "order_id": 24783795
    },
    {
      "tracking_number": "30645832024",
      "order_id": 24783898
    },
    {
      "tracking_number": "30645832054",
      "order_id": 24785377
    },
    {
      "tracking_number": "30645832057",
      "order_id": 24785877
    },
    {
      "tracking_number": "30645832075",
      "order_id": 24786529
    },
    {
      "tracking_number": "30645832078",
      "order_id": 24786699
    },
    {
      "tracking_number": "30645832102",
      "order_id": 24788345
    },
    {
      "tracking_number": "30645832123",
      "order_id": 24789705
    },
    {
      "tracking_number": "30645832137",
      "order_id": 24791365
    },
    {
      "tracking_number": "30645832147",
      "order_id": 24791801
    },
    {
      "tracking_number": "30645832265",
      "order_id": 24798197
    },
    {
      "tracking_number": "30645832279",
      "order_id": 24798882
    },
    {
      "tracking_number": "30645832280",
      "order_id": 24798946
    },
    {
      "tracking_number": "30645833971",
      "order_id": 24802789
    },
    {
      "tracking_number": "30645833996",
      "order_id": 24803866
    },
    {
      "tracking_number": "30645834094",
      "order_id": 24808809
    },
    {
      "tracking_number": "30645834126",
      "order_id": 24809210
    },
    {
      "tracking_number": "30645834170",
      "order_id": 24812179
    },
    {
      "tracking_number": "30645834194",
      "order_id": 24813136
    },
    {
      "tracking_number": "30645834228",
      "order_id": 24814479
    },
    {
      "tracking_number": "30645834230",
      "order_id": 24814647
    },
    {
      "tracking_number": "30645834241",
      "order_id": 24815614
    },
    {
      "tracking_number": "30645834257",
      "order_id": 24816216
    },
    {
      "tracking_number": "30645834275",
      "order_id": 24817196
    },
    {
      "tracking_number": "30645834281",
      "order_id": 24817201
    },
    {
      "tracking_number": "30645834302",
      "order_id": 24818796
    },
    {
      "tracking_number": "30645834327",
      "order_id": 24819800
    },
    {
      "tracking_number": "30645834381",
      "order_id": 24822300
    },
    {
      "tracking_number": "30645834511",
      "order_id": 24828559
    },
    {
      "tracking_number": "30645834564",
      "order_id": 24831228
    },
    {
      "tracking_number": "30645834571",
      "order_id": 24831407
    },
    {
      "tracking_number": "30645834615",
      "order_id": 24833928
    },
    {
      "tracking_number": "30645834696",
      "order_id": 24838489
    },
    {
      "tracking_number": "30645834709",
      "order_id": 24838941
    },
    {
      "tracking_number": "30645834710",
      "order_id": 24838940
    },
    {
      "tracking_number": "30645834735",
      "order_id": 24840569
    },
    {
      "tracking_number": "30645834796",
      "order_id": 24843631
    },
    {
      "tracking_number": "30645834841",
      "order_id": 24846348
    },
    {
      "tracking_number": "30645834846",
      "order_id": 24846459
    },
    {
      "tracking_number": "30645834871",
      "order_id": 24848665
    },
    {
      "tracking_number": "30645837603",
      "order_id": 24853391
    },
    {
      "tracking_number": "30645837624",
      "order_id": 24853577
    },
    {
      "tracking_number": "30645837652",
      "order_id": 24855013
    },
    {
      "tracking_number": "30645837749",
      "order_id": 24860250
    },
    {
      "tracking_number": "30645837750",
      "order_id": 24860253
    },
    {
      "tracking_number": "30645837781",
      "order_id": 24862165
    },
    {
      "tracking_number": "30645837816",
      "order_id": 24864227
    },
    {
      "tracking_number": "30645837824",
      "order_id": 24864118
    },
    {
      "tracking_number": "30645837843",
      "order_id": 24865155
    },
    {
      "tracking_number": "30645837862",
      "order_id": 24867053
    },
    {
      "tracking_number": "30645837910",
      "order_id": 24869572
    },
    {
      "tracking_number": "30645837966",
      "order_id": 24872560
    },
    {
      "tracking_number": "30645837967",
      "order_id": 24872562
    },
    {
      "tracking_number": "30645837981",
      "order_id": 24873478
    },
    {
      "tracking_number": "30645837983",
      "order_id": 24873477
    },
    {
      "tracking_number": "30645838018",
      "order_id": 24875923
    },
    {
      "tracking_number": "30645838051",
      "order_id": 24879429
    },
    {
      "tracking_number": "30645838052",
      "order_id": 24879430
    },
    {
      "tracking_number": "30645838210",
      "order_id": 24888754
    },
    {
      "tracking_number": "30645838272",
      "order_id": 24892025
    },
    {
      "tracking_number": "30645838273",
      "order_id": 24892109
    },
    {
      "tracking_number": "30645838356",
      "order_id": 24898987
    },
    {
      "tracking_number": "30645838398",
      "order_id": 24902280
    },
    {
      "tracking_number": "30645838441",
      "order_id": 24905584
    },
    {
      "tracking_number": "30645838444",
      "order_id": 24905941
    },
    {
      "tracking_number": "30645838495",
      "order_id": 24909137
    },
    {
      "tracking_number": "30645838497",
      "order_id": 24909234
    },
    {
      "tracking_number": "30645838499",
      "order_id": 24909131
    },
    {
      "tracking_number": "30645838501",
      "order_id": 24909236
    },
    {
      "tracking_number": "30645838503",
      "order_id": 24909239
    },
    {
      "tracking_number": "30645838507",
      "order_id": 24909329
    },
    {
      "tracking_number": "30645838520",
      "order_id": 24910967
    },
    {
      "tracking_number": "30645838545",
      "order_id": 24912132
    },
    {
      "tracking_number": "30645838550",
      "order_id": 24912128
    },
    {
      "tracking_number": "30645838556",
      "order_id": 24912153
    },
    {
      "tracking_number": "30645838600",
      "order_id": 24915337
    },
    {
      "tracking_number": "30645838629",
      "order_id": 24917127
    },
    {
      "tracking_number": "30645838636",
      "order_id": 24917467
    },
    {
      "tracking_number": "30645838639",
      "order_id": 24917468
    },
    {
      "tracking_number": "30645838641",
      "order_id": 24917375
    },
    {
      "tracking_number": "30645838647",
      "order_id": 24917378
    },
    {
      "tracking_number": "30645838711",
      "order_id": 24920673
    },
    {
      "tracking_number": "30645838718",
      "order_id": 24922189
    },
    {
      "tracking_number": "30645838770",
      "order_id": 24924952
    },
    {
      "tracking_number": "30645838805",
      "order_id": 24926990
    },
    {
      "tracking_number": "30645838806",
      "order_id": 24926993
    },
    {
      "tracking_number": "30645838898",
      "order_id": 24937234
    },
    {
      "tracking_number": "30645838907",
      "order_id": 24937231
    },
    {
      "tracking_number": "30645838934",
      "order_id": 24938653
    },
    {
      "tracking_number": "30645838944",
      "order_id": 24938707
    },
    {
      "tracking_number": "30645838961",
      "order_id": 24938999
    },
    {
      "tracking_number": "30645838966",
      "order_id": 24938925
    },
    {
      "tracking_number": "30645838976",
      "order_id": 24939900
    },
    {
      "tracking_number": "30645838979",
      "order_id": 24939974
    },
    {
      "tracking_number": "30645838980",
      "order_id": 24940035
    },
    {
      "tracking_number": "30645838981",
      "order_id": 24939969
    },
    {
      "tracking_number": "30645838982",
      "order_id": 24939970
    },
    {
      "tracking_number": "30645838983",
      "order_id": 24940037
    },
    {
      "tracking_number": "30645838984",
      "order_id": 24940038
    },
    {
      "tracking_number": "30645838985",
      "order_id": 24940119
    },
    {
      "tracking_number": "30645838988",
      "order_id": 24940034
    },
    {
      "tracking_number": "30645838989",
      "order_id": 24939971
    },
    {
      "tracking_number": "30645838990",
      "order_id": 24939972
    },
    {
      "tracking_number": "30645838991",
      "order_id": 24940036
    },
    {
      "tracking_number": "30645838999",
      "order_id": 24940211
    },
    {
      "tracking_number": "30645839008",
      "order_id": 24940121
    },
    {
      "tracking_number": "30645839026",
      "order_id": 24941194
    },
    {
      "tracking_number": "30645839042",
      "order_id": 24944145
    },
    {
      "tracking_number": "30645839043",
      "order_id": 24944307
    },
    {
      "tracking_number": "30645839047",
      "order_id": 24944201
    },
    {
      "tracking_number": "30645839053",
      "order_id": 24944508
    },
    {
      "tracking_number": "30645839086",
      "order_id": 24945390
    },
    {
      "tracking_number": "30645839087",
      "order_id": 24945387
    },
    {
      "tracking_number": "30645839104",
      "order_id": 24947094
    },
    {
      "tracking_number": "30645839105",
      "order_id": 24946843
    },
    {
      "tracking_number": "30645839133",
      "order_id": 24948245
    },
    {
      "tracking_number": "30645839157",
      "order_id": 24950015
    },
    {
      "tracking_number": "30645839158",
      "order_id": 24950130
    },
    {
      "tracking_number": "30645839164",
      "order_id": 24950013
    },
    {
      "tracking_number": "30645839165",
      "order_id": 24950014
    },
    {
      "tracking_number": "30645839170",
      "order_id": 24951701
    },
    {
      "tracking_number": "30645839182",
      "order_id": 24951371
    },
    {
      "tracking_number": "30645839185",
      "order_id": 24951199
    },
    {
      "tracking_number": "30645839230",
      "order_id": 24955139
    },
    {
      "tracking_number": "30645839248",
      "order_id": 24956080
    },
    {
      "tracking_number": "30645839250",
      "order_id": 24956076
    },
    {
      "tracking_number": "30645839255",
      "order_id": 24956082
    },
    {
      "tracking_number": "30645839257",
      "order_id": 24956328
    },
    {
      "tracking_number": "30645839266",
      "order_id": 24957775
    },
    {
      "tracking_number": "30645839296",
      "order_id": 24959647
    },
    {
      "tracking_number": "30645839297",
      "order_id": 24959861
    },
    {
      "tracking_number": "30645839299",
      "order_id": 24959741
    },
    {
      "tracking_number": "30645839315",
      "order_id": 24961267
    },
    {
      "tracking_number": "30645839321",
      "order_id": 24961720
    },
    {
      "tracking_number": "30645839336",
      "order_id": 24962599
    },
    {
      "tracking_number": "30645839338",
      "order_id": 24963017
    },
    {
      "tracking_number": "30645839341",
      "order_id": 24963014
    },
    {
      "tracking_number": "30645839342",
      "order_id": 24963021
    },
    {
      "tracking_number": "30645839345",
      "order_id": 24963013
    },
    {
      "tracking_number": "30645839349",
      "order_id": 24963015
    },
    {
      "tracking_number": "30645839350",
      "order_id": 24963016
    },
    {
      "tracking_number": "30645839351",
      "order_id": 24962594
    },
    {
      "tracking_number": "30645839352",
      "order_id": 24962937
    },
    {
      "tracking_number": "30645839356",
      "order_id": 24963126
    },
    {
      "tracking_number": "30645839385",
      "order_id": 24964889
    },
    {
      "tracking_number": "30645839398",
      "order_id": 24965930
    },
    {
      "tracking_number": "30645839428",
      "order_id": 24968820
    },
    {
      "tracking_number": "30645839429",
      "order_id": 24968819
    },
    {
      "tracking_number": "30645839430",
      "order_id": 24968633
    },
    {
      "tracking_number": "30645839431",
      "order_id": 24968634
    },
    {
      "tracking_number": "30645839434",
      "order_id": 24968632
    },
    {
      "tracking_number": "30645839435",
      "order_id": 24968817
    },
    {
      "tracking_number": "30645839436",
      "order_id": 24968635
    },
    {
      "tracking_number": "30645839437",
      "order_id": 24968821
    },
    {
      "tracking_number": "30645839454",
      "order_id": 24970132
    },
    {
      "tracking_number": "30645839458",
      "order_id": 24970847
    },
    {
      "tracking_number": "30645839460",
      "order_id": 24970846
    },
    {
      "tracking_number": "30645839463",
      "order_id": 24970801
    },
    {
      "tracking_number": "30645839464",
      "order_id": 24970842
    },
    {
      "tracking_number": "30645839465",
      "order_id": 24970844
    },
    {
      "tracking_number": "30645839470",
      "order_id": 24971623
    },
    {
      "tracking_number": "30645839478",
      "order_id": 24971792
    },
    {
      "tracking_number": "30645839481",
      "order_id": 24971941
    },
    {
      "tracking_number": "30645839483",
      "order_id": 24971940
    },
    {
      "tracking_number": "30645839492",
      "order_id": 24972340
    },
    {
      "tracking_number": "30645839493",
      "order_id": 24972342
    },
    {
      "tracking_number": "30645839501",
      "order_id": 24973161
    },
    {
      "tracking_number": "30645839502",
      "order_id": 24973119
    },
    {
      "tracking_number": "30645839503",
      "order_id": 24973492
    },
    {
      "tracking_number": "30645839505",
      "order_id": 24973466
    },
    {
      "tracking_number": "30645839519",
      "order_id": 24973975
    },
    {
      "tracking_number": "30645839524",
      "order_id": 24974038
    },
    {
      "tracking_number": "30645839525",
      "order_id": 24974286
    },
    {
      "tracking_number": "30645839526",
      "order_id": 24974287
    },
    {
      "tracking_number": "30645839527",
      "order_id": 24974288
    },
    {
      "tracking_number": "30645839528",
      "order_id": 24974247
    },
    {
      "tracking_number": "30645839539",
      "order_id": 24976369
    },
    {
      "tracking_number": "30645839542",
      "order_id": 24976379
    },
    {
      "tracking_number": "30645839547",
      "order_id": 24976391
    },
    {
      "tracking_number": "30645839559",
      "order_id": 24977437
    },
    {
      "tracking_number": "30645839561",
      "order_id": 24977903
    },
    {
      "tracking_number": "30645839564",
      "order_id": 24978190
    },
    {
      "tracking_number": "30645866501",
      "order_id": 24978127
    },
    {
      "tracking_number": "30645866527",
      "order_id": 24979852
    },
    {
      "tracking_number": "30645866559",
      "order_id": 24980073
    },
    {
      "tracking_number": "30645866585",
      "order_id": 24981628
    },
    {
      "tracking_number": "30645866594",
      "order_id": 24982391
    },
    {
      "tracking_number": "30645866595",
      "order_id": 24982531
    },
    {
      "tracking_number": "30645866612",
      "order_id": 24984190
    },
    {
      "tracking_number": "30645866618",
      "order_id": 24985199
    },
    {
      "tracking_number": "30645866619",
      "order_id": 24985116
    },
    {
      "tracking_number": "30645866621",
      "order_id": 24985308
    },
    {
      "tracking_number": "30645866632",
      "order_id": 24986462
    },
    {
      "tracking_number": "30645866633",
      "order_id": 24986644
    },
    {
      "tracking_number": "30645866634",
      "order_id": 24986647
    },
    {
      "tracking_number": "30645866635",
      "order_id": 24986649
    },
    {
      "tracking_number": "30645866636",
      "order_id": 24986461
    },
    {
      "tracking_number": "30645866638",
      "order_id": 24986460
    },
    {
      "tracking_number": "30645866646",
      "order_id": 24987681
    },
    {
      "tracking_number": "30645866647",
      "order_id": 24987618
    },
    {
      "tracking_number": "30645866671",
      "order_id": 24989458
    },
    {
      "tracking_number": "30645866672",
      "order_id": 24989373
    },
    {
      "tracking_number": "30645866674",
      "order_id": 24989200
    },
    {
      "tracking_number": "30645866675",
      "order_id": 24989368
    },
    {
      "tracking_number": "30645866676",
      "order_id": 24989379
    },
    {
      "tracking_number": "30645866685",
      "order_id": 24990697
    },
    {
      "tracking_number": "30645866687",
      "order_id": 24990824
    },
    {
      "tracking_number": "30645866695",
      "order_id": 24992036
    },
    {
      "tracking_number": "30645866697",
      "order_id": 24992035
    },
    {
      "tracking_number": "30645866699",
      "order_id": 24992137
    },
    {
      "tracking_number": "30645866712",
      "order_id": 24992911
    },
    {
      "tracking_number": "30645866719",
      "order_id": 24993451
    },
    {
      "tracking_number": "30645866720",
      "order_id": 24993454
    },
    {
      "tracking_number": "30645866722",
      "order_id": 24993545
    },
    {
      "tracking_number": "30645866723",
      "order_id": 24993547
    },
    {
      "tracking_number": "30645866724",
      "order_id": 24993624
    },
    {
      "tracking_number": "30645866725",
      "order_id": 24993453
    },
    {
      "tracking_number": "30645866727",
      "order_id": 24993623
    },
    {
      "tracking_number": "30645866757",
      "order_id": 24995596
    },
    {
      "tracking_number": "30645866758",
      "order_id": 24995598
    },
    {
      "tracking_number": "30645866759",
      "order_id": 24995595
    },
    {
      "tracking_number": "30645866769",
      "order_id": 24996667
    },
    {
      "tracking_number": "30645866771",
      "order_id": 24996288
    },
    {
      "tracking_number": "30645866772",
      "order_id": 24996363
    },
    {
      "tracking_number": "30645866773",
      "order_id": 24996576
    },
    {
      "tracking_number": "30645866805",
      "order_id": 24999499
    },
    {
      "tracking_number": "30645866821",
      "order_id": 25000056
    },
    {
      "tracking_number": "30645866825",
      "order_id": 25000321
    },
    {
      "tracking_number": "30645866826",
      "order_id": 25000316
    },
    {
      "tracking_number": "30645866850",
      "order_id": 25002127
    },
    {
      "tracking_number": "30645866866",
      "order_id": 25002998
    },
    {
      "tracking_number": "30645866867",
      "order_id": 25002999
    },
    {
      "tracking_number": "30645866879",
      "order_id": 25010592
    },
    {
      "tracking_number": "30645866913",
      "order_id": 25019145
    },
    {
      "tracking_number": "30645866917",
      "order_id": 25012967
    },
    {
      "tracking_number": "30645866919",
      "order_id": 25012969
    },
    {
      "tracking_number": "30645866920",
      "order_id": 25012970
    },
    {
      "tracking_number": "30645866922",
      "order_id": 25012847
    },
    {
      "tracking_number": "30645866936",
      "order_id": 25013066
    },
    {
      "tracking_number": "30645866937",
      "order_id": 25013159
    },
    {
      "tracking_number": "30645866938",
      "order_id": 25013068
    },
    {
      "tracking_number": "30645866962",
      "order_id": 25014035
    },
    {
      "tracking_number": "30645866963",
      "order_id": 25014037
    },
    {
      "tracking_number": "30645866966",
      "order_id": 25014371
    },
    {
      "tracking_number": "30645866968",
      "order_id": 25014125
    },
    {
      "tracking_number": "30645866969",
      "order_id": 25014308
    },
    {
      "tracking_number": "30645866973",
      "order_id": 25014311
    },
    {
      "tracking_number": "30645866975",
      "order_id": 25014127
    },
    {
      "tracking_number": "30645866976",
      "order_id": 25014213
    },
    {
      "tracking_number": "30645866978",
      "order_id": 25014309
    },
    {
      "tracking_number": "30645866979",
      "order_id": 25014374
    },
    {
      "tracking_number": "30645866987",
      "order_id": 25014553
    },
    {
      "tracking_number": "30645866989",
      "order_id": 25014552
    },
    {
      "tracking_number": "30645877383",
      "order_id": 25015565
    },
    {
      "tracking_number": "30645877384",
      "order_id": 25015826
    },
    {
      "tracking_number": "30645877387",
      "order_id": 25015706
    },
    {
      "tracking_number": "30645877388",
      "order_id": 25015473
    },
    {
      "tracking_number": "30645877389",
      "order_id": 25015475
    },
    {
      "tracking_number": "30645877391",
      "order_id": 25015705
    },
    {
      "tracking_number": "30645877392",
      "order_id": 25015564
    },
    {
      "tracking_number": "30645877393",
      "order_id": 25015632
    },
    {
      "tracking_number": "30645877394",
      "order_id": 25015634
    },
    {
      "tracking_number": "30645877400",
      "order_id": 25015933
    },
    {
      "tracking_number": "30645877403",
      "order_id": 25015932
    },
    {
      "tracking_number": "30645877404",
      "order_id": 25016000
    },
    {
      "tracking_number": "30645877409",
      "order_id": 25015999
    },
    {
      "tracking_number": "30645877422",
      "order_id": 25020558
    },
    {
      "tracking_number": "30645877427",
      "order_id": 25017695
    },
    {
      "tracking_number": "30645877450",
      "order_id": 25021119
    },
    {
      "tracking_number": "30645877451",
      "order_id": 25020989
    },
    {
      "tracking_number": "30645877456",
      "order_id": 25021238
    },
    {
      "tracking_number": "30645877458",
      "order_id": 25021244
    },
    {
      "tracking_number": "30645877459",
      "order_id": 25021047
    },
    {
      "tracking_number": "30645877464",
      "order_id": 25021438
    },
    {
      "tracking_number": "30645877467",
      "order_id": 25021439
    },
    {
      "tracking_number": "30645877474",
      "order_id": 25021440
    },
    {
      "tracking_number": "30645877490",
      "order_id": 25022302
    },
    {
      "tracking_number": "30645877492",
      "order_id": 25022229
    },
    {
      "tracking_number": "30645877496",
      "order_id": 25022757
    },
    {
      "tracking_number": "30645877498",
      "order_id": 25022760
    },
    {
      "tracking_number": "30645877503",
      "order_id": 25022679
    },
    {
      "tracking_number": "30645877504",
      "order_id": 25022829
    },
    {
      "tracking_number": "30645877508",
      "order_id": 25022759
    },
    {
      "tracking_number": "30645877550",
      "order_id": 25026180
    },
    {
      "tracking_number": "30645877553",
      "order_id": 25026178
    }
  ],
  "batch_logs": [
    {
      "batch_index": 1,
      "batch_size": 50,
      "ok": true,
      "elapsed_ms": 8132.1,
      "matched_so_far": 46
    },
    {
      "batch_index": 2,
      "batch_size": 50,
      "ok": true,
      "elapsed_ms": 7431.0,
      "matched_so_far": 78
    },
    {
      "batch_index": 3,
      "batch_size": 50,
      "ok": true,
      "elapsed_ms": 7934.4,
      "matched_so_far": 126
    },
    {
      "batch_index": 4,
      "batch_size": 50,
      "ok": true,
      "elapsed_ms": 7817.4,
      "matched_so_far": 175
    },
    {
      "batch_index": 5,
      "batch_size": 50,
      "ok": true,
      "elapsed_ms": 7916.9,
      "matched_so_far": 218
    },
    {
      "batch_index": 6,
      "batch_size": 50,
      "ok": true,
      "elapsed_ms": 7853.2,
      "matched_so_far": 249
    },
    {
      "batch_index": 7,
      "batch_size": 50,
      "ok": true,
      "elapsed_ms": 7985.9,
      "matched_so_far": 299
    },
    {
      "batch_index": 8,
      "batch_size": 50,
      "ok": true,
      "elapsed_ms": 8588.1,
      "matched_so_far": 348
    },
    {
      "batch_index": 9,
      "batch_size": 50,
      "ok": true,
      "elapsed_ms": 7115.4,
      "matched_so_far": 397
    },
    {
      "batch_index": 10,
      "batch_size": 50,
      "ok": true,
      "elapsed_ms": 8145.5,
      "matched_so_far": 445
    }
  ]
}